jsonhandler/__init__.py
jsonhandler/custom_base.py
jsonhandler/database.py
jsonhandlerdb-0.0.2.dist-info/LICENSE
jsonhandlerdb-0.0.2.dist-info/METADATA
jsonhandlerdb-0.0.2.dist-info/WHEEL
jsonhandlerdb-0.0.2.dist-info/top_level.txt
jsonhandlerdb-0.0.2.dist-info/RECORD
