Metadata-Version: 2.2
Name: jsonhandlerdb
Version: 0.0.2
Summary: A small example package
Author-email: Keagan Landfried <keaganlandfried@gmail.com>
License: MIT License
Project-URL: Homepage, https://github.com/Zennara/JsonHandler
Project-URL: Issues, https://github.com/Zennara/JsonHandler/issues
Classifier: Programming Language :: Python :: 3
Classifier: Operating System :: OS Independent
Requires-Python: >=3.8
License-File: LICENSE
